harsh_hvz_marvel_api/__init__.py
harsh_hvz_marvel_api/all_functions.py
harsh_hvz_marvel_api-0.0.1.dist-info/METADATA
harsh_hvz_marvel_api-0.0.1.dist-info/WHEEL
harsh_hvz_marvel_api-0.0.1.dist-info/top_level.txt
harsh_hvz_marvel_api-0.0.1.dist-info/RECORD
