Metadata-Version: 2.1
Name: harsh-hvz-marvel-api
Version: 0.0.1
Summary: Package to create API call and filter the results
Home-page: UNKNOWN
Author: Harsh Vardhan Singh
Author-email: harshvardhan42662@gmail.com
License: UNKNOWN
Platform: UNKNOWN
